forcediphttpsadapter/__init__.py
forcediphttpsadapter/adapters.py
forcediphttpsadapter-1.1.0.dist-info/LICENSE
forcediphttpsadapter-1.1.0.dist-info/METADATA
forcediphttpsadapter-1.1.0.dist-info/WHEEL
forcediphttpsadapter-1.1.0.dist-info/top_level.txt
forcediphttpsadapter-1.1.0.dist-info/RECORD
