Metadata-Version: 2.1
Name: forcediphttpsadapter
Version: 1.1.0
Summary: This module implements a set of requests TransportAdapter, PoolManager, ConnectionPool and HTTPSConnection allowing use of a specific IP address when connecting via SSL to a web service without running into SNI trouble. 
Home-page: https://github.com/Roadmaster/forcediphttpsadapter
Download-URL: https://github.com/Roadmaster/forcediphttpsadapter/archive/master.zip
Author: Roadmaster
Author-email: daniel@tomechangosubanana.com
Provides: adapters
License-File: LICENSE
Requires-Dist: packaging
Requires-Dist: requests
